setup.py
tqirpa/__init__.py
tqirpa.egg-info/PKG-INFO
tqirpa.egg-info/SOURCES.txt
tqirpa.egg-info/dependency_links.txt
tqirpa.egg-info/requires.txt
tqirpa.egg-info/top_level.txt