Metadata-Version: 1.1
Name: tqirpa
Version: 1.0.1
Summary: Pacote de Framework RPA da TQI
Home-page: https://github.com/usuario/meu-pacote-python
Author: Leander Ribeiro
Author-email: leander.ribeiro@tqi.com.br
License: MIT
Keywords: rpa
Platform: UNKNOWN
Classifier: Intended Audience :: Developers
Classifier: License :: OSI Approved :: MIT License
Classifier: Natural Language :: English
Classifier: Programming Language :: Python :: 3
